{
    "AdminAuthorization": [
        {
            "type": "string",
            "prop": "login",
            "translate": "Логин"
        },
        {
            "type": "string",
            "prop": "password",
            "translate": "Пароль",
            "secret": true
        },
        {
            "type": "combobox",
            "prop": "role",
            "translate": "Должность",
            "items": [ "Менеджер", "Администратор" ]
        }
    ],
    "AdminRegistration": [
        {
            "type": "string",
            "prop": "login"
        },
        {
            "type": "string",
            "prop": "password",
            "secret": true
        },
        {
            "type": "string",
            "prop": "repeat_password",
            "secret": true
        },
        {
            "type": "string",
            "prop": "name"
        },
        {
            "type": "string",
            "prop": "surname"
        },
        {
            "type": "string",
            "prop": "middle_name"
        },
        {
            "type": "string",
            "prop": "email"
        },
        {
            "type": "string",
            "prop": "telephone"
        },
        {
            "type": "combobox",
            "prop": "role",
            "items": [ "Мужской", "Женский" ]
        }
    ],
    "ClientAuthorization": [
        {
            "type": "string",
            "prop": "login"
        },
        {
            "type": "string",
            "prop": "password",
            "secret": true
        }
    ],
    "ClientRegistration": [
        {
            "type": "string",
            "prop": "login"
        },
        {
            "type": "string",
            "prop": "password",
            "secret": true
        },
        {
            "type": "string",
            "prop": "repeat_password",
            "secret": true
        },
        {
            "type": "string",
            "prop": "name"
        },
        {
            "type": "string",
            "prop": "surname"
        },
        {
            "type": "string",
            "prop": "middle_name"
        },
        {
            "type": "string",
            "prop": "email"
        },
        {
            "type": "string",
            "prop": "telephone"
        },
        {
            "type": "combobox",
            "prop": "gender",
            "items": [ "Мужской", "Женский" ]
        },
        {
            "type": "string",
            "prop": "image"
        }
    ],
    "PaymentSelection": [
        {
            "type": "combobox",
            "prop": "payment",
            "items": [ "Полная оплата по карте", "Оплата половины суммы", "Оплата по прибытию" ]
        }
    ],
    "LeaveComment": [
        {
            "type": "string",
            "prop": "text",
            "translate": "Текст"
        },
        {
            "type": "number",
            "prop": "rating",
            "translate": "Оценка от 0 до 5",
            "min": 0,
            "max": 5
        }
    ]
}